[
  {
    "id": "breachstone",
    "classId": "Breachstone",
    "className": {
      "en": "Breachstones",
      "kr": "균열석",
      "tw": "裂痕石",
      "ru": "Камни Разлома",
      "jp": "ブリーチストーン"
    },
    "name": {
      "en": "Breachstone",
      "kr": "균열석",
      "tw": "裂痕石",
      "ru": "Камень Разлома",
      "jp": "ブリーチストーン"
    },
    "dropLevel": 68,
    "spec": null,
    "currency": {
      "stackSize": 1,
      "description": {
        "en": null,
        "kr": null,
        "tw": null,
        "ru": null,
        "jp": null
      },
      "directions": {
        "en": "Required to reveal Breach Strongholds on the Atlas.",
        "kr": "아틀라스에서 균열 요새를 드러내는 데 필요합니다.",
        "tw": "在輿圖上揭露裂痕據點所需的物品",
        "ru": "Требуется для обнаружения крепостей Разлома на Атласе.",
        "jp": "アトラス上でブリーチの砦を公開するために必要となる"
      }
    },
    "flavour": {
      "en": "The Twisted Breachlord reaches out from his\r\nDomain with maddened agony and anger.",
      "kr": "뒤틀린 균열 군주가 광기의 고통과 분노에 차오른 채\r\n자신의 영역으로부터 손아귀를 뻗친다.",
      "tw": "扭曲的裂痕王在瘋狂的痛苦和怒氣中\r\n從他的國度向外拓展。",
      "ru": "Искажённый Повелитель Разлома стремится сюда\r\nиз своей вотчины, обезумев от ярости и агонии.",
      "jp": "歪んだブリーチロードは狂った苦痛と怒りで\r\nその領域から手を伸ばす。"
    },
    "implicits": null,
    "image": null
  },
  {
    "id": "xophs-breachstone",
    "classId": "Breachstone",
    "className": {
      "en": "Breachstones",
      "kr": "균열석",
      "tw": "裂痕石",
      "ru": "Камни Разлома",
      "jp": "ブリーチストーン"
    },
    "name": {
      "en": "Xoph's Breachstone",
      "kr": "조프의 균열석",
      "tw": "索伏裂痕石",
      "ru": "Камень Разлома Ксофа",
      "jp": "ゾフのブリーチストーン"
    },
    "dropLevel": 68,
    "spec": null,
    "currency": {
      "stackSize": 1,
      "description": {
        "en": "Rare Monsters drop an additional Reward Type\r\nArea has 2 additional random Modifiers\r\n100% increased Experience Gain\r\nMonster Level: 81",
        "kr": "희귀 몬스터가 추가 보상 유형 1개 떨어뜨림\r\n지역에 무작위 속성 2개 추가\r\n경험치 획득량 100% 증가\r\n몬스터 레벨: 81",
        "tw": "稀有怪物掉落 1 個額外獎勵類型\r\n區域有 2 個額外隨機詞綴\r\n增加 100% 獲得經驗\r\n怪物等級：81",
        "ru": "Из редких монстров выпадает награда дополнительного типа\r\nНа область действуют 2 дополнительных случайных свойства\r\n100% увеличение получаемого опыта\r\nУровень монстров: 81",
        "jp": "レアモンスターが追加の報酬タイプをドロップする\r\nエリアにランダムな2個のモッドが追加される\r\n得られる経験値が100%増加する\r\nモンスターレベル: 81"
      },
      "directions": {
        "en": "Travel to Xoph's Domain by using this item in a personal Map Device. Can only be used once.",
        "kr": "전용 지도 장치에서 해당 아이템을 사용해 조프의 영토로 갈 수 있습니다. 한 번만 사용할 수 있습니다.",
        "tw": "透過個人的地圖裝置來使用此道具前往索伏領域。只能被使用一次。",
        "ru": "Используйте этот предмет в вашей Машине картоходца, чтобы отправиться во Владения Ксофа. Можно использовать один раз.",
        "jp": "自身のマップデバイスでこのアイテムを使用してゾフの領域に移動する。一度のみ使用できる。"
      }
    },
    "flavour": null,
    "implicits": null,
    "image": null
  },
  {
    "id": "tuls-breachstone",
    "classId": "Breachstone",
    "className": {
      "en": "Breachstones",
      "kr": "균열석",
      "tw": "裂痕石",
      "ru": "Камни Разлома",
      "jp": "ブリーチストーン"
    },
    "name": {
      "en": "Tul's Breachstone",
      "kr": "툴의 균열석",
      "tw": "托沃裂痕石",
      "ru": "Камень Разлома Тул",
      "jp": "トゥルのブリーチストーン"
    },
    "dropLevel": 70,
    "spec": null,
    "currency": {
      "stackSize": 1,
      "description": {
        "en": "Rare Monsters drop an additional Reward Type\r\nArea has 2 additional random Modifiers\r\n100% increased Experience Gain\r\nMonster Level: 81",
        "kr": "희귀 몬스터가 추가 보상 유형 1개 떨어뜨림\r\n지역에 무작위 속성 2개 추가\r\n경험치 획득량 100% 증가\r\n몬스터 레벨: 81",
        "tw": "稀有怪物掉落 1 個額外獎勵類型\r\n區域有 2 個額外隨機詞綴\r\n增加 100% 獲得經驗\r\n怪物等級：81",
        "ru": "Из редких монстров выпадает награда дополнительного типа\r\nНа область действуют 2 дополнительных случайных свойства\r\n100% увеличение получаемого опыта\r\nУровень монстров: 81",
        "jp": "レアモンスターが追加の報酬タイプをドロップする\r\nエリアにランダムな2個のモッドが追加される\r\n得られる経験値が100%増加する\r\nモンスターレベル: 81"
      },
      "directions": {
        "en": "Travel to Tul's Domain by using this item in a personal Map Device. Can only be used once.",
        "kr": "전용 지도 장치에서 해당 아이템을 사용해 툴의 영토로 갈 수 있습니다. 한 번만 사용할 수 있습니다.",
        "tw": "透過個人的地圖裝置來使用此道具前往托沃領域。只能被使用一次。",
        "ru": "Используйте этот предмет в вашей Машине картоходца, чтобы отправиться во Владения Тул. Можно использовать один раз.",
        "jp": "自身のマップデバイスでこのアイテムを使用してトゥルの領域に移動する。一度のみ使用できる。"
      }
    },
    "flavour": null,
    "implicits": null,
    "image": null
  },
  {
    "id": "eshs-breachstone",
    "classId": "Breachstone",
    "className": {
      "en": "Breachstones",
      "kr": "균열석",
      "tw": "裂痕石",
      "ru": "Камни Разлома",
      "jp": "ブリーチストーン"
    },
    "name": {
      "en": "Esh's Breachstone",
      "kr": "에쉬의 균열석",
      "tw": "艾許裂痕石",
      "ru": "Камень Разлома Иш",
      "jp": "エッシュのブリーチストーン"
    },
    "dropLevel": 72,
    "spec": null,
    "currency": {
      "stackSize": 1,
      "description": {
        "en": "Rare Monsters drop an additional Reward Type\r\nArea has 2 additional random Modifiers\r\n100% increased Experience Gain\r\nMonster Level: 81",
        "kr": "희귀 몬스터가 추가 보상 유형 1개 떨어뜨림\r\n지역에 무작위 속성 2개 추가\r\n경험치 획득량 100% 증가\r\n몬스터 레벨: 81",
        "tw": "稀有怪物掉落 1 個額外獎勵類型\r\n區域有 2 個額外隨機詞綴\r\n增加 100% 獲得經驗\r\n怪物等級：81",
        "ru": "Из редких монстров выпадает награда дополнительного типа\r\nНа область действуют 2 дополнительных случайных свойства\r\n100% увеличение получаемого опыта\r\nУровень монстров: 81",
        "jp": "レアモンスターが追加の報酬タイプをドロップする\r\nエリアにランダムな2個のモッドが追加される\r\n得られる経験値が100%増加する\r\nモンスターレベル: 81"
      },
      "directions": {
        "en": "Travel to Esh's Domain by using this item in a personal Map Device. Can only be used once.",
        "kr": "전용 지도 장치에서 해당 아이템을 사용해 에쉬의 영토로 갈 수 있습니다. 한 번만 사용할 수 있습니다.",
        "tw": "透過個人的地圖裝置來使用此道具前往艾許領域。只能被使用一次。",
        "ru": "Используйте этот предмет в вашей Машине картоходца, чтобы отправиться во Владения Иш. Можно использовать один раз.",
        "jp": "自身のマップデバイスでこのアイテムを使用してエシュの領域に移動する。一度のみ使用できる。"
      }
    },
    "flavour": null,
    "implicits": null,
    "image": null
  },
  {
    "id": "uul-netols-breachstone",
    "classId": "Breachstone",
    "className": {
      "en": "Breachstones",
      "kr": "균열석",
      "tw": "裂痕石",
      "ru": "Камни Разлома",
      "jp": "ブリーチストーン"
    },
    "name": {
      "en": "Uul-Netol's Breachstone",
      "kr": "울네톨의 균열석",
      "tw": "烏爾尼多裂痕石",
      "ru": "Камень Разлома Уул-Нетол",
      "jp": "ウール・ネトルのブリーチストーン"
    },
    "dropLevel": 76,
    "spec": null,
    "currency": {
      "stackSize": 1,
      "description": {
        "en": "Rare Monsters drop an additional Reward Type\r\nArea has 2 additional random Modifiers\r\n150% increased Experience Gain\r\nMonster Level: 82",
        "kr": "희귀 몬스터가 추가 보상 유형 1개 떨어뜨림\r\n지역에 무작위 속성 2개 추가\r\n경험치 획득량 150% 증가\r\n몬스터 레벨: 82",
        "tw": "稀有怪物掉落 1 個額外獎勵類型\r\n區域有 2 個額外隨機詞綴\r\n增加 150% 獲得經驗\r\n怪物等級：82",
        "ru": "Из редких монстров выпадает награда дополнительного типа\r\nНа область действуют 2 дополнительных случайных свойства\r\n150% увеличение получаемого опыта\r\nУровень монстров: 82",
        "jp": "レアモンスターが追加の報酬タイプをドロップする\r\nエリアにランダムな2個のモッドが追加される\r\n得られる経験値が150%増加する\r\nモンスターレベル: 82"
      },
      "directions": {
        "en": "Travel to Uul-Netol's Domain by using this item in a personal Map Device. Can only be used once.",
        "kr": "전용 지도 장치에서 해당 아이템을 사용해 울네톨의 영토로 갈 수 있습니다. 한 번만 사용할 수 있습니다.",
        "tw": "透過個人的地圖裝置來使用此道具前往烏爾尼多領域。只能被使用一次。",
        "ru": "Используйте этот предмет в вашей Машине картоходца, чтобы отправиться во Владения Уул-Нетол. Можно использовать один раз.",
        "jp": "自身のマップデバイスでこのアイテムを使用してウール・ネトルの領域に移動する。一度のみ使用できる。"
      }
    },
    "flavour": null,
    "implicits": null,
    "image": null
  },
  {
    "id": "chayulas-breachstone",
    "classId": "Breachstone",
    "className": {
      "en": "Breachstones",
      "kr": "균열석",
      "tw": "裂痕石",
      "ru": "Камни Разлома",
      "jp": "ブリーチストーン"
    },
    "name": {
      "en": "Chayula's Breachstone",
      "kr": "차율라의 균열석",
      "tw": "夏烏拉裂痕石",
      "ru": "Камень Разлома Чаюлы",
      "jp": "チャユラのブリーチストーン"
    },
    "dropLevel": 80,
    "spec": null,
    "currency": {
      "stackSize": 1,
      "description": {
        "en": "Rare Monsters drop an additional Reward Type\r\nArea has 2 additional random Modifiers\r\n200% increased Experience Gain\r\nMonster Level: 83",
        "kr": "희귀 몬스터가 추가 보상 유형 1개 떨어뜨림\r\n지역에 무작위 속성 2개 추가\r\n경험치 획득량 200% 증가\r\n몬스터 레벨: 83",
        "tw": "稀有怪物掉落 1 個額外獎勵類型\r\n區域有 2 個額外隨機詞綴\r\n增加 200% 獲得經驗\r\n怪物等級：83",
        "ru": "Из редких монстров выпадает награда дополнительного типа\r\nНа область действуют 2 дополнительных случайных свойства\r\n200% увеличение получаемого опыта\r\nУровень монстров: 83",
        "jp": "レアモンスターが追加の報酬タイプをドロップする\r\nエリアにランダムな2個のモッドが追加される\r\n得られる経験値が200%増加する\r\nモンスターレベル: 83"
      },
      "directions": {
        "en": "Travel to Chayula's Domain by using this item in a personal Map Device. Can only be used once.",
        "kr": "전용 지도 장치에서 해당 아이템을 사용해 차율라의 영토로 갈 수 있습니다. 한 번만 사용할 수 있습니다.",
        "tw": "透過個人的地圖裝置來使用此道具前往夏烏拉領域。只能被使用一次。",
        "ru": "Используйте этот предмет в вашей Машине картоходца, чтобы отправиться во Владения Чаюлы. Можно использовать один раз.",
        "jp": "自身のマップデバイスでこのアイテムを使用してチャユラの領域に移動する。一度のみ使用できる。"
      }
    },
    "flavour": null,
    "implicits": null,
    "image": null
  },
  {
    "id": "xophs-charged-breachstone",
    "classId": "Breachstone",
    "className": {
      "en": "Breachstones",
      "kr": "균열석",
      "tw": "裂痕石",
      "ru": "Камни Разлома",
      "jp": "ブリーチストーン"
    },
    "name": {
      "en": "Xoph's Charged Breachstone",
      "kr": "조프의 충전된 균열석",
      "tw": "索伏充能裂痕石",
      "ru": "Заряженный камень Разлома Ксофа",
      "jp": "ゾフの充填ブリーチストーン"
    },
    "dropLevel": 68,
    "spec": null,
    "currency": {
      "stackSize": 1,
      "description": {
        "en": "Rare Monsters drop an additional Reward Type\r\nArea has 2 additional random Modifiers\r\n100% increased Experience Gain\r\n20% increased Rarity of Items found in this Area\r\n20% increased Pack Size\r\nMonster Level: 74",
        "kr": "희귀 몬스터가 추가 보상 유형 1개 떨어뜨림\r\n지역에 무작위 속성 2개 추가\r\n경험치 획득량 100% 증가\r\n이 지역에서 발견하는 아이템의 희귀도 20% 증가\r\n무리 규모 20% 증가\r\n몬스터 레벨: 74",
        "tw": "稀有怪物掉落 1 個額外獎勵類型\r\n區域有 2 個額外隨機詞綴\r\n增加 100% 獲得經驗\r\n增加 20% 此區域的物品稀有度\r\n增加 20% 怪物群大小\r\n怪物等級：74",
        "ru": "Из редких монстров выпадает награда дополнительного типа\r\nНа область действуют 2 дополнительных случайных свойства\r\nУровень монстров: 74\r\n100% увеличение получаемого опыта\r\n20% повышение редкости найденных предметов в этой области\r\n20% увеличение размера групп монстров",
        "jp": "レアモンスターが追加の報酬タイプをドロップする\r\nエリアにランダムな2個のモッドが追加される\r\n得られる経験値が100%増加する\r\nエリア内で得られるアイテムのレアリティが20%増加する\r\nパックサイズが20%増加する\r\nモンスターレベル: 74"
      },
      "directions": {
        "en": "Travel to Xoph's Domain by using this item in a personal Map Device. Can only be used once.",
        "kr": "전용 지도 장치에서 해당 아이템을 사용해 조프의 영토로 갈 수 있습니다. 한 번만 사용할 수 있습니다.",
        "tw": "透過個人的地圖裝置來使用此道具前往索伏領域。只能被使用一次。",
        "ru": "Используйте этот предмет в вашей Машине картоходца, чтобы отправиться во Владения Ксофа. Можно использовать один раз.",
        "jp": "自身のマップデバイスでこのアイテムを使用してゾフの領域に移動する。一度のみ使用できる。"
      }
    },
    "flavour": null,
    "implicits": null,
    "image": null
  },
  {
    "id": "tuls-charged-breachstone",
    "classId": "Breachstone",
    "className": {
      "en": "Breachstones",
      "kr": "균열석",
      "tw": "裂痕石",
      "ru": "Камни Разлома",
      "jp": "ブリーチストーン"
    },
    "name": {
      "en": "Tul's Charged Breachstone",
      "kr": "툴의 충전된 균열석",
      "tw": "托沃充能裂痕石",
      "ru": "Заряженный камень Разлома Тул",
      "jp": "トゥルの充填ブリーチストーン"
    },
    "dropLevel": 70,
    "spec": null,
    "currency": {
      "stackSize": 1,
      "description": {
        "en": "Rare Monsters drop an additional Reward Type\r\nArea has 2 additional random Modifiers\r\n100% increased Experience Gain\r\n20% increased Rarity of Items found in this Area\r\n20% increased Pack Size\r\nMonster Level: 74",
        "kr": "희귀 몬스터가 추가 보상 유형 1개 떨어뜨림\r\n지역에 무작위 속성 2개 추가\r\n경험치 획득량 100% 증가\r\n이 지역에서 발견하는 아이템의 희귀도 20% 증가\r\n무리 규모 20% 증가\r\n몬스터 레벨: 74",
        "tw": "稀有怪物掉落 1 個額外獎勵類型\r\n區域有 2 個額外隨機詞綴\r\n增加 100% 獲得經驗\r\n增加 20% 此區域的物品稀有度\r\n增加 20% 怪物群大小\r\n怪物等級：74",
        "ru": "Из редких монстров выпадает награда дополнительного типа\r\nНа область действуют 2 дополнительных случайных свойства\r\nУровень монстров: 74\r\n100% увеличение получаемого опыта\r\n20% повышение редкости найденных предметов в этой области\r\n20% увеличение размера групп монстров",
        "jp": "レアモンスターが追加の報酬タイプをドロップする\r\n得られる経験値が100%増加する\r\nエリア内で得られるアイテムのレアリティが20%増加する\r\nパックサイズが20%増加する\r\nモンスターレベル: 74"
      },
      "directions": {
        "en": "Travel to Tul's Domain by using this item in a personal Map Device. Can only be used once.",
        "kr": "전용 지도 장치에서 해당 아이템을 사용해 툴의 영토로 갈 수 있습니다. 한 번만 사용할 수 있습니다.",
        "tw": "透過個人的地圖裝置來使用此道具前往托沃領域。只能被使用一次。",
        "ru": "Используйте этот предмет в вашей Машине картоходца, чтобы отправиться во Владения Тул. Можно использовать один раз.",
        "jp": "自身のマップデバイスでこのアイテムを使用してトゥルの領域に移動する。一度のみ使用できる。"
      }
    },
    "flavour": null,
    "implicits": null,
    "image": null
  },
  {
    "id": "eshs-charged-breachstone",
    "classId": "Breachstone",
    "className": {
      "en": "Breachstones",
      "kr": "균열석",
      "tw": "裂痕石",
      "ru": "Камни Разлома",
      "jp": "ブリーチストーン"
    },
    "name": {
      "en": "Esh's Charged Breachstone",
      "kr": "에쉬의 충전된 균열석",
      "tw": "艾許充能裂痕石",
      "ru": "Заряженный камень Разлома Иш",
      "jp": "エシュの充填ブリーチストーン"
    },
    "dropLevel": 72,
    "spec": null,
    "currency": {
      "stackSize": 1,
      "description": {
        "en": "Rare Monsters drop an additional Reward Type\r\nArea has 2 additional random Modifiers\r\n100% increased Experience Gain\r\n20% increased Rarity of Items found in this Area\r\n20% increased Pack Size\r\nMonster Level: 74",
        "kr": "희귀 몬스터가 추가 보상 유형 1개 떨어뜨림\r\n지역에 무작위 속성 2개 추가\r\n경험치 획득량 100% 증가\r\n이 지역에서 발견하는 아이템의 희귀도 20% 증가\r\n무리 규모 20% 증가\r\n몬스터 레벨: 74",
        "tw": "稀有怪物掉落 1 個額外獎勵類型\r\n區域有 2 個額外隨機詞綴\r\n增加 100% 獲得經驗\r\n增加 20% 此區域的物品稀有度\r\n增加 20% 怪物群大小\r\n怪物等級：74",
        "ru": "Из редких монстров выпадает награда дополнительного типа\r\nНа область действуют 2 дополнительных случайных свойства\r\nУровень монстров: 74\r\n100% увеличение получаемого опыта\r\n20% повышение редкости найденных предметов в этой области\r\n20% увеличение размера групп монстров",
        "jp": "レアモンスターが追加の報酬タイプをドロップする\r\nエリアにランダムな2個のモッドが追加される\r\n得られる経験値が100%増加する\r\nエリア内で得られるアイテムのレアリティが20%増加する\r\nパックサイズが20%増加する\r\nモンスターレベル: 74"
      },
      "directions": {
        "en": "Travel to Esh's Domain by using this item in a personal Map Device. Can only be used once.",
        "kr": "전용 지도 장치에서 해당 아이템을 사용해 에쉬의 영토로 갈 수 있습니다. 한 번만 사용할 수 있습니다.",
        "tw": "透過個人的地圖裝置來使用此道具前往艾許領域。只能被使用一次。",
        "ru": "Используйте этот предмет в вашей Машине картоходца, чтобы отправиться во Владения Иш. Можно использовать один раз.",
        "jp": "自身のマップデバイスでこのアイテムを使用してエシュの領域に移動する。一度のみ使用できる。"
      }
    },
    "flavour": null,
    "implicits": null,
    "image": null
  },
  {
    "id": "uul-netols-charged-breachstone",
    "classId": "Breachstone",
    "className": {
      "en": "Breachstones",
      "kr": "균열석",
      "tw": "裂痕石",
      "ru": "Камни Разлома",
      "jp": "ブリーチストーン"
    },
    "name": {
      "en": "Uul-Netol's Charged Breachstone",
      "kr": "울네톨의 충전된 균열석",
      "tw": "烏爾尼多充能裂痕石",
      "ru": "Заряженный камень Разлома Уул-Нетол",
      "jp": "ウール・ネトルの充填ブリーチストーン"
    },
    "dropLevel": 76,
    "spec": null,
    "currency": {
      "stackSize": 1,
      "description": {
        "en": "Rare Monsters drop an additional Reward Type\r\nArea has 2 additional random Modifiers\r\n150% increased Experience Gain\r\n20% increased Rarity of Items found in this Area\r\n20% increased Pack Size\r\nMonster Level: 78",
        "kr": "희귀 몬스터가 추가 보상 유형 1개 떨어뜨림\r\n지역에 무작위 속성 2개 추가\r\n경험치 획득량 150% 증가\r\n이 지역에서 발견하는 아이템의 희귀도 20% 증가\r\n무리 규모 20% 증가\r\n몬스터 레벨: 78",
        "tw": "稀有怪物掉落 1 個額外獎勵類型\r\n區域有 2 個額外隨機詞綴\r\n增加 150% 獲得經驗\r\n增加 20% 此區域的物品稀有度\r\n增加 20% 怪物群大小\r\n怪物等級：78",
        "ru": "Из редких монстров выпадает награда дополнительного типа\r\nНа область действуют 2 дополнительных случайных свойства\r\nУровень монстров: 78\r\n150% увеличение получаемого опыта\r\n20% повышение редкости найденных предметов в этой области\r\n20% увеличение размера групп монстров",
        "jp": "レアモンスターが追加の報酬タイプをドロップする\r\nエリアにランダムな2個のモッドが追加される\r\n得られる経験値が150%増加する\r\nエリア内で得られるアイテムのレアリティが20%増加する\r\nパックサイズが20%増加する\r\nモンスターレベル: 78"
      },
      "directions": {
        "en": "Travel to Uul-Netol's Domain by using this item in a personal Map Device. Can only be used once.",
        "kr": "전용 지도 장치에서 해당 아이템을 사용해 울네톨의 영토로 갈 수 있습니다. 한 번만 사용할 수 있습니다.",
        "tw": "透過個人的地圖裝置來使用此道具前往烏爾尼多領域。只能被使用一次。",
        "ru": "Используйте этот предмет в вашей Машине картоходца, чтобы отправиться во Владения Уул-Нетол. Можно использовать один раз.",
        "jp": "自身のマップデバイスでこのアイテムを使用してウール・ネトルの領域に移動する。一度のみ使用できる。"
      }
    },
    "flavour": null,
    "implicits": null,
    "image": null
  },
  {
    "id": "chayulas-charged-breachstone",
    "classId": "Breachstone",
    "className": {
      "en": "Breachstones",
      "kr": "균열석",
      "tw": "裂痕石",
      "ru": "Камни Разлома",
      "jp": "ブリーチストーン"
    },
    "name": {
      "en": "Chayula's Charged Breachstone",
      "kr": "차율라의 충전된 균열석",
      "tw": "夏烏拉充能裂痕石",
      "ru": "Заряженный камень Разлома Чаюлы",
      "jp": "チャユラの充填ブリーチストーン"
    },
    "dropLevel": 80,
    "spec": null,
    "currency": {
      "stackSize": 1,
      "description": {
        "en": "Rare Monsters drop an additional Reward Type\r\nArea has 2 additional random Modifiers\r\n200% increased Experience Gain\r\n20% increased Rarity of Items found in this Area\r\n20% increased Pack Size\r\nMonster Level: 81",
        "kr": "희귀 몬스터가 추가 보상 유형 1개 떨어뜨림\r\n지역에 무작위 속성 2개 추가\r\n경험치 획득량 200% 증가\r\n이 지역에서 발견하는 아이템의 희귀도 20% 증가\r\n무리 규모 20% 증가\r\n몬스터 레벨: 81",
        "tw": "稀有怪物掉落 1 個額外獎勵類型\r\n區域有 2 個額外隨機詞綴\r\n增加 200% 獲得經驗\r\n增加 20% 此區域的物品稀有度\r\n增加 20% 怪物群大小\r\n怪物等級：81",
        "ru": "Из редких монстров выпадает награда дополнительного типа\r\nНа область действуют 2 дополнительных случайных свойства\r\nУровень монстров: 81\r\n200% увеличение получаемого опыта\r\n20% повышение редкости найденных предметов в этой области\r\n20% увеличение размера групп монстров",
        "jp": "レアモンスターが追加の報酬タイプをドロップする\r\nエリアにランダムな2個のモッドが追加される\r\n得られる経験値が200%増加する\r\nエリア内で得られるアイテムのレアリティが20%増加する\r\nパックサイズが20%増加する\r\nモンスターレベル: 81"
      },
      "directions": {
        "en": "Travel to Chayula's Domain by using this item in a personal Map Device. Can only be used once.",
        "kr": "전용 지도 장치에서 해당 아이템을 사용해 차율라의 영토로 갈 수 있습니다. 한 번만 사용할 수 있습니다.",
        "tw": "透過個人的地圖裝置來使用此道具前往夏烏拉領域。只能被使用一次。",
        "ru": "Используйте этот предмет в вашей Машине картоходца, чтобы отправиться во Владения Чаюлы. Можно использовать один раз.",
        "jp": "自身のマップデバイスでこのアイテムを使用してチャユラの領域に移動する。一度のみ使用できる。"
      }
    },
    "flavour": null,
    "implicits": null,
    "image": null
  },
  {
    "id": "xophs-enriched-breachstone",
    "classId": "Breachstone",
    "className": {
      "en": "Breachstones",
      "kr": "균열석",
      "tw": "裂痕石",
      "ru": "Камни Разлома",
      "jp": "ブリーチストーン"
    },
    "name": {
      "en": "Xoph's Enriched Breachstone",
      "kr": "조프의 풍부한 균열석",
      "tw": "索伏富裕裂痕石",
      "ru": "Обогащённый камень Разлома Ксофа",
      "jp": "ゾフの強化ブリーチストーン"
    },
    "dropLevel": 68,
    "spec": null,
    "currency": {
      "stackSize": 1,
      "description": {
        "en": "Rare Monsters drop an additional Reward Type\r\nArea has 2 additional random Modifiers\r\n100% increased Experience Gain\r\n40% increased Rarity of Items found in this Area\r\n40% increased Pack Size\r\nMonster Level: 79",
        "kr": "희귀 몬스터가 추가 보상 유형 1개 떨어뜨림\r\n지역에 무작위 속성 2개 추가\r\n경험치 획득량 100% 증가\r\n이 지역에서 발견하는 아이템의 희귀도 40% 증가\r\n무리 규모 40% 증가\r\n몬스터 레벨: 79",
        "tw": "稀有怪物掉落 1 個額外獎勵類型\r\n區域有 2 個額外隨機詞綴\r\n增加 100% 獲得經驗\r\n增加 40% 此區域的物品稀有度\r\n增加 40% 怪物群大小\r\n怪物等級：79",
        "ru": "Из редких монстров выпадает награда дополнительного типа\r\nНа область действуют 2 дополнительных случайных свойства\r\nУровень монстров: 79\r\n100% увеличение получаемого опыта\r\n40% повышение редкости найденных предметов в этой области\r\n40% увеличение размера групп монстров",
        "jp": "レアモンスターが追加の報酬タイプをドロップする\r\nエリアにランダムな2個のモッドが追加される\r\n得られる経験値が100%増加する\r\nエリア内で得られるアイテムのレアリティが40%増加する\r\nパックサイズが40%増加する\r\nモンスターレベル: 79"
      },
      "directions": {
        "en": "Travel to Xoph's Domain by using this item in a personal Map Device. Can only be used once.",
        "kr": "전용 지도 장치에서 해당 아이템을 사용해 조프의 영토로 갈 수 있습니다. 한 번만 사용할 수 있습니다.",
        "tw": "透過個人的地圖裝置來使用此道具前往索伏領域。只能被使用一次。",
        "ru": "Используйте этот предмет в вашей Машине картоходца, чтобы отправиться во Владения Ксофа. Можно использовать один раз.",
        "jp": "自身のマップデバイスでこのアイテムを使用してゾフの領域に移動する。一度のみ使用できる。"
      }
    },
    "flavour": null,
    "implicits": null,
    "image": null
  },
  {
    "id": "tuls-enriched-breachstone",
    "classId": "Breachstone",
    "className": {
      "en": "Breachstones",
      "kr": "균열석",
      "tw": "裂痕石",
      "ru": "Камни Разлома",
      "jp": "ブリーチストーン"
    },
    "name": {
      "en": "Tul's Enriched Breachstone",
      "kr": "툴의 풍부한 균열석",
      "tw": "托沃富裕裂痕石",
      "ru": "Обогащённый камень Разлома Тул",
      "jp": "トゥルの強化ブリーチストーン"
    },
    "dropLevel": 70,
    "spec": null,
    "currency": {
      "stackSize": 1,
      "description": {
        "en": "Rare Monsters drop an additional Reward Type\r\nArea has 2 additional random Modifiers\r\n100% increased Experience Gain\r\n40% increased Rarity of Items found in this Area\r\n40% increased Pack Size\r\nMonster Level: 79",
        "kr": "희귀 몬스터가 추가 보상 유형 1개 떨어뜨림\r\n지역에 무작위 속성 2개 추가\r\n경험치 획득량 100% 증가\r\n이 지역에서 발견하는 아이템의 희귀도 40% 증가\r\n무리 규모 40% 증가\r\n몬스터 레벨: 79",
        "tw": "稀有怪物掉落 1 個額外獎勵類型\r\n區域有 2 個額外隨機詞綴\r\n增加 100% 獲得經驗\r\n增加 40% 此區域的物品稀有度\r\n增加 40% 怪物群大小\r\n怪物等級：79",
        "ru": "Из редких монстров выпадает награда дополнительного типа\r\nНа область действуют 2 дополнительных случайных свойства\r\nУровень монстров: 79\r\n100% увеличение получаемого опыта\r\n40% повышение редкости найденных предметов в этой области\r\n40% увеличение размера групп монстров",
        "jp": "レアモンスターが追加の報酬タイプをドロップする\r\nエリアにランダムな2個のモッドが追加される\r\n得られる経験値が100%増加する\r\nエリア内で得られるアイテムのレアリティが40%増加する\r\nパックサイズが40%増加する\r\nモンスターレベル: 79"
      },
      "directions": {
        "en": "Travel to Tul's Domain by using this item in a personal Map Device. Can only be used once.",
        "kr": "전용 지도 장치에서 해당 아이템을 사용해 툴의 영토로 갈 수 있습니다. 한 번만 사용할 수 있습니다.",
        "tw": "透過個人的地圖裝置來使用此道具前往托沃領域。只能被使用一次。",
        "ru": "Используйте этот предмет в вашей Машине картоходца, чтобы отправиться во Владения Тул. Можно использовать один раз.",
        "jp": "自身のマップデバイスでこのアイテムを使用してトゥルの領域に移動する。一度のみ使用できる。"
      }
    },
    "flavour": null,
    "implicits": null,
    "image": null
  },
  {
    "id": "eshs-enriched-breachstone",
    "classId": "Breachstone",
    "className": {
      "en": "Breachstones",
      "kr": "균열석",
      "tw": "裂痕石",
      "ru": "Камни Разлома",
      "jp": "ブリーチストーン"
    },
    "name": {
      "en": "Esh's Enriched Breachstone",
      "kr": "에쉬의 풍부한 균열석",
      "tw": "艾許富裕裂痕石",
      "ru": "Обогащённый камень Разлома Иш",
      "jp": "エシュの強化ブリーチストーン"
    },
    "dropLevel": 72,
    "spec": null,
    "currency": {
      "stackSize": 1,
      "description": {
        "en": "Rare Monsters drop an additional Reward Type\r\nArea has 2 additional random Modifiers\r\n100% increased Experience Gain\r\n40% increased Rarity of Items found in this Area\r\n40% increased Pack Size\r\nMonster Level: 79",
        "kr": "희귀 몬스터가 추가 보상 유형 1개 떨어뜨림\r\n지역에 무작위 속성 2개 추가\r\n경험치 획득량 100% 증가\r\n이 지역에서 발견하는 아이템의 희귀도 40% 증가\r\n무리 규모 40% 증가\r\n몬스터 레벨: 79",
        "tw": "稀有怪物掉落 1 個額外獎勵類型\r\n區域有 2 個額外隨機詞綴\r\n增加 100% 獲得經驗\r\n增加 40% 此區域的物品稀有度\r\n增加 40% 怪物群大小\r\n怪物等級：79",
        "ru": "Из редких монстров выпадает награда дополнительного типа\r\nНа область действуют 2 дополнительных случайных свойства\r\nУровень монстров: 79\r\n100% увеличение получаемого опыта\r\n40% повышение редкости найденных предметов в этой области\r\n40% увеличение размера групп монстров",
        "jp": "レアモンスターが追加の報酬タイプをドロップする\r\nエリアにランダムな2個のモッドが追加される\r\n得られる経験値が100%増加する\r\nエリア内で得られるアイテムのレアリティが40%増加する\r\nパックサイズが40%増加する\r\nモンスターレベル: 79"
      },
      "directions": {
        "en": "Travel to Esh's Domain by using this item in a personal Map Device. Can only be used once.",
        "kr": "전용 지도 장치에서 해당 아이템을 사용해 에쉬의 영토로 갈 수 있습니다. 한 번만 사용할 수 있습니다.",
        "tw": "透過個人的地圖裝置來使用此道具前往艾許領域。只能被使用一次。",
        "ru": "Используйте этот предмет в вашей Машине картоходца, чтобы отправиться во Владения Иш. Можно использовать один раз.",
        "jp": "自身のマップデバイスでこのアイテムを使用してエシュの領域に移動する。一度のみ使用できる。"
      }
    },
    "flavour": null,
    "implicits": null,
    "image": null
  },
  {
    "id": "uul-netols-enriched-breachstone",
    "classId": "Breachstone",
    "className": {
      "en": "Breachstones",
      "kr": "균열석",
      "tw": "裂痕石",
      "ru": "Камни Разлома",
      "jp": "ブリーチストーン"
    },
    "name": {
      "en": "Uul-Netol's Enriched Breachstone",
      "kr": "울네톨의 풍부한 균열석",
      "tw": "烏爾尼多富裕裂痕石",
      "ru": "Обогащённый камень Разлома Уул-Нетол",
      "jp": "ウール・ネトルの強化ブリーチストーン"
    },
    "dropLevel": 76,
    "spec": null,
    "currency": {
      "stackSize": 1,
      "description": {
        "en": "Rare Monsters drop an additional Reward Type\r\nArea has 2 additional random Modifiers\r\n150% increased Experience Gain\r\n40% increased Rarity of Items found in this Area\r\n40% increased Pack Size\r\nMonster Level: 81",
        "kr": "희귀 몬스터가 추가 보상 유형 1개 떨어뜨림\r\n지역에 무작위 속성 2개 추가\r\n경험치 획득량 150% 증가\r\n이 지역에서 발견하는 아이템의 희귀도 40% 증가\r\n무리 규모 40% 증가\r\n몬스터 레벨: 81",
        "tw": "稀有怪物掉落 1 個額外獎勵類型\r\n區域有 2 個額外隨機詞綴\r\n增加 150% 獲得經驗\r\n增加 40% 此區域的物品稀有度\r\n增加 40% 怪物群大小\r\n怪物等級：81",
        "ru": "Из редких монстров выпадает награда дополнительного типа\r\nНа область действуют 2 дополнительных случайных свойства\r\nУровень монстров: 81\r\n150% увеличение получаемого опыта\r\n40% повышение редкости найденных предметов в этой области\r\n40% увеличение размера групп монстров",
        "jp": "レアモンスターが追加の報酬タイプをドロップする\r\nエリアにランダムな2個のモッドが追加される\r\n得られる経験値が150%増加する\r\nエリア内で得られるアイテムのレアリティが40%増加する\r\nパックサイズが40%増加する\r\nモンスターレベル: 81"
      },
      "directions": {
        "en": "Travel to Uul-Netol's Domain by using this item in a personal Map Device. Can only be used once.",
        "kr": "전용 지도 장치에서 해당 아이템을 사용해 울네톨의 영토로 갈 수 있습니다. 한 번만 사용할 수 있습니다.",
        "tw": "透過個人的地圖裝置來使用此道具前往烏爾尼多領域。只能被使用一次。",
        "ru": "Используйте этот предмет в вашей Машине картоходца, чтобы отправиться во Владения Уул-Нетол. Можно использовать один раз.",
        "jp": "自身のマップデバイスでこのアイテムを使用してウール・ネトルの領域に移動する。一度のみ使用できる。"
      }
    },
    "flavour": null,
    "implicits": null,
    "image": null
  },
  {
    "id": "chayulas-enriched-breachstone",
    "classId": "Breachstone",
    "className": {
      "en": "Breachstones",
      "kr": "균열석",
      "tw": "裂痕石",
      "ru": "Камни Разлома",
      "jp": "ブリーチストーン"
    },
    "name": {
      "en": "Chayula's Enriched Breachstone",
      "kr": "차율라의 풍부한 균열석",
      "tw": "夏烏拉富裕裂痕石",
      "ru": "Обогащённый камень Разлома Чаюлы",
      "jp": "チャユラの強化ブリーチストーン"
    },
    "dropLevel": 80,
    "spec": null,
    "currency": {
      "stackSize": 1,
      "description": {
        "en": "Rare Monsters drop an additional Reward Type\r\nArea has 2 additional random Modifiers\r\n200% increased Experience Gain\r\n40% increased Rarity of Items found in this Area\r\n40% increased Pack Size\r\nMonster Level: 82",
        "kr": "희귀 몬스터가 추가 보상 유형 1개 떨어뜨림\r\n지역에 무작위 속성 2개 추가\r\n경험치 획득량 200% 증가\r\n이 지역에서 발견하는 아이템의 희귀도 40% 증가\r\n무리 규모 40% 증가\r\n몬스터 레벨: 82",
        "tw": "稀有怪物掉落 1 個額外獎勵類型\r\n區域有 2 個額外隨機詞綴\r\n增加 200% 獲得經驗\r\n增加 40% 此區域的物品稀有度\r\n增加 40% 怪物群大小\r\n怪物等級：82",
        "ru": "Из редких монстров выпадает награда дополнительного типа\r\nНа область действуют 2 дополнительных случайных свойства\r\nУровень монстров: 82\r\n200% увеличение получаемого опыта\r\n40% повышение редкости найденных предметов в этой области\r\n40% увеличение размера групп монстров",
        "jp": "レアモンスターが追加の報酬タイプをドロップする\r\nエリアにランダムな2個のモッドが追加される\r\n得られる経験値が200%増加する\r\nエリア内で得られるアイテムのレアリティが40%増加する\r\nパックサイズが40%増加する\r\nモンスターレベル: 82"
      },
      "directions": {
        "en": "Travel to Chayula's Domain by using this item in a personal Map Device. Can only be used once.",
        "kr": "전용 지도 장치에서 해당 아이템을 사용해 차율라의 영토로 갈 수 있습니다. 한 번만 사용할 수 있습니다.",
        "tw": "透過個人的地圖裝置來使用此道具前往夏烏拉領域。只能被使用一次。",
        "ru": "Используйте этот предмет в вашей Машине картоходца, чтобы отправиться во Владения Чаюлы. Можно использовать один раз.",
        "jp": "自身のマップデバイスでこのアイテムを使用してチャユラの領域に移動する。一度のみ使用できる。"
      }
    },
    "flavour": null,
    "implicits": null,
    "image": null
  },
  {
    "id": "xophs-pure-breachstone",
    "classId": "Breachstone",
    "className": {
      "en": "Breachstones",
      "kr": "균열석",
      "tw": "裂痕石",
      "ru": "Камни Разлома",
      "jp": "ブリーチストーン"
    },
    "name": {
      "en": "Xoph's Pure Breachstone",
      "kr": "조프의 순수한 균열석",
      "tw": "索伏純淨裂痕石",
      "ru": "Очищенный камень Разлома Ксофа",
      "jp": "ゾフの純化ブリーチストーン"
    },
    "dropLevel": 68,
    "spec": null,
    "currency": {
      "stackSize": 1,
      "description": {
        "en": "Rare Monsters drop an additional Reward Type\r\nArea has 2 additional random Modifiers\r\n100% increased Experience Gain\r\n60% increased Rarity of Items found in this Area\r\n60% increased Pack Size\r\nMonster Level: 81",
        "kr": "희귀 몬스터가 추가 보상 유형 1개 떨어뜨림\r\n지역에 무작위 속성 2개 추가\r\n경험치 획득량 100% 증가\r\n이 지역에서 발견하는 아이템의 희귀도 60% 증가\r\n무리 규모 60% 증가\r\n몬스터 레벨: 81",
        "tw": "稀有怪物掉落 1 個額外獎勵類型\r\n區域有 2 個額外隨機詞綴\r\n增加 100% 獲得經驗\r\n增加 60% 此區域的物品稀有度\r\n增加 60% 怪物群大小\r\n怪物等級：81",
        "ru": "Из редких монстров выпадает награда дополнительного типа\r\nНа область действуют 2 дополнительных случайных свойства\r\nУровень монстров: 81\r\n100% увеличение получаемого опыта\r\n60% повышение редкости найденных предметов в этой области\r\n60% увеличение размера групп монстров",
        "jp": "レアモンスターが追加の報酬タイプをドロップする\r\nエリアにランダムな2個のモッドが追加される\r\n得られる経験値が100%増加する\r\nエリア内で得られるアイテムのレアリティが60%増加する\r\nパックサイズが60%増加する\r\nモンスターレベル: 81"
      },
      "directions": {
        "en": "Travel to Xoph's Domain by using this item in a personal Map Device. Can only be used once.",
        "kr": "전용 지도 장치에서 해당 아이템을 사용해 조프의 영토로 갈 수 있습니다. 한 번만 사용할 수 있습니다.",
        "tw": "透過個人的地圖裝置來使用此道具前往索伏領域。只能被使用一次。",
        "ru": "Используйте этот предмет в вашей Машине картоходца, чтобы отправиться во Владения Ксофа. Можно использовать один раз.",
        "jp": "自身のマップデバイスでこのアイテムを使用してゾフの領域に移動する。一度のみ使用できる。"
      }
    },
    "flavour": null,
    "implicits": null,
    "image": null
  },
  {
    "id": "tuls-pure-breachstone",
    "classId": "Breachstone",
    "className": {
      "en": "Breachstones",
      "kr": "균열석",
      "tw": "裂痕石",
      "ru": "Камни Разлома",
      "jp": "ブリーチストーン"
    },
    "name": {
      "en": "Tul's Pure Breachstone",
      "kr": "툴의 순수한 균열석",
      "tw": "托沃純淨裂痕石",
      "ru": "Очищенный камень Разлома Тул",
      "jp": "トゥルの純化ブリーチストーン"
    },
    "dropLevel": 70,
    "spec": null,
    "currency": {
      "stackSize": 1,
      "description": {
        "en": "Rare Monsters drop an additional Reward Type\r\nArea has 2 additional random Modifiers\r\n100% increased Experience Gain\r\n60% increased Rarity of Items found in this Area\r\n60% increased Pack Size\r\nMonster Level: 81",
        "kr": "희귀 몬스터가 추가 보상 유형 1개 떨어뜨림\r\n지역에 무작위 속성 2개 추가\r\n경험치 획득량 100% 증가\r\n이 지역에서 발견하는 아이템의 희귀도 60% 증가\r\n무리 규모 60% 증가\r\n몬스터 레벨: 81",
        "tw": "稀有怪物掉落 1 個額外獎勵類型\r\n區域有 2 個額外隨機詞綴\r\n增加 100% 獲得經驗\r\n增加 60% 此區域的物品稀有度\r\n增加 60% 怪物群大小\r\n怪物等級：81",
        "ru": "Из редких монстров выпадает награда дополнительного типа\r\nНа область действуют 2 дополнительных случайных свойства\r\nУровень монстров: 81\r\n100% увеличение получаемого опыта\r\n60% повышение редкости найденных предметов в этой области\r\n60% увеличение размера групп монстров",
        "jp": "レアモンスターが追加の報酬タイプをドロップする\r\nエリアにランダムな2個のモッドが追加される\r\n得られる経験値が100%増加する\r\nエリア内で得られるアイテムのレアリティが60%増加する\r\nパックサイズが60%増加する\r\nモンスターレベル: 81"
      },
      "directions": {
        "en": "Travel to Tul's Domain by using this item in a personal Map Device. Can only be used once.",
        "kr": "전용 지도 장치에서 해당 아이템을 사용해 툴의 영토로 갈 수 있습니다. 한 번만 사용할 수 있습니다.",
        "tw": "透過個人的地圖裝置來使用此道具前往托沃領域。只能被使用一次。",
        "ru": "Используйте этот предмет в вашей Машине картоходца, чтобы отправиться во Владения Тул. Можно использовать один раз.",
        "jp": "自身のマップデバイスでこのアイテムを使用してトゥルの領域に移動する。一度のみ使用できる。"
      }
    },
    "flavour": null,
    "implicits": null,
    "image": null
  },
  {
    "id": "eshs-pure-breachstone",
    "classId": "Breachstone",
    "className": {
      "en": "Breachstones",
      "kr": "균열석",
      "tw": "裂痕石",
      "ru": "Камни Разлома",
      "jp": "ブリーチストーン"
    },
    "name": {
      "en": "Esh's Pure Breachstone",
      "kr": "에쉬의 순수한 균열석",
      "tw": "艾許純淨裂痕石",
      "ru": "Очищенный камень Разлома Иш",
      "jp": "エシュの純化ブリーチストーン"
    },
    "dropLevel": 72,
    "spec": null,
    "currency": {
      "stackSize": 1,
      "description": {
        "en": "Rare Monsters drop an additional Reward Type\r\nArea has 2 additional random Modifiers\r\n100% increased Experience Gain\r\n60% increased Rarity of Items found in this Area\r\n60% increased Pack Size\r\nMonster Level: 81",
        "kr": "희귀 몬스터가 추가 보상 유형 1개 떨어뜨림\r\n지역에 무작위 속성 2개 추가\r\n경험치 획득량 100% 증가\r\n이 지역에서 발견하는 아이템의 희귀도 60% 증가\r\n무리 규모 60% 증가\r\n몬스터 레벨: 81",
        "tw": "稀有怪物掉落 1 個額外獎勵類型\r\n區域有 2 個額外隨機詞綴\r\n增加 100% 獲得經驗\r\n增加 60% 此區域的物品稀有度\r\n增加 60% 怪物群大小\r\n怪物等級：81",
        "ru": "Из редких монстров выпадает награда дополнительного типа\r\nНа область действуют 2 дополнительных случайных свойства\r\nУровень монстров: 81\r\n100% увеличение получаемого опыта\r\n60% повышение редкости найденных предметов в этой области\r\n60% увеличение размера групп монстров",
        "jp": "レアモンスターが追加の報酬タイプをドロップする\r\nエリアにランダムな2個のモッドが追加される\r\n得られる経験値が100%増加する\r\nエリア内で得られるアイテムのレアリティが60%増加する\r\nパックサイズが60%増加する\r\nモンスターレベル: 81"
      },
      "directions": {
        "en": "Travel to Esh's Domain by using this item in a personal Map Device. Can only be used once.",
        "kr": "전용 지도 장치에서 해당 아이템을 사용해 에쉬의 영토로 갈 수 있습니다. 한 번만 사용할 수 있습니다.",
        "tw": "透過個人的地圖裝置來使用此道具前往艾許領域。只能被使用一次。",
        "ru": "Используйте этот предмет в вашей Машине картоходца, чтобы отправиться во Владения Иш. Можно использовать один раз.",
        "jp": "自身のマップデバイスでこのアイテムを使用してエシュの領域に移動する。一度のみ使用できる。"
      }
    },
    "flavour": null,
    "implicits": null,
    "image": null
  },
  {
    "id": "uul-netols-pure-breachstone",
    "classId": "Breachstone",
    "className": {
      "en": "Breachstones",
      "kr": "균열석",
      "tw": "裂痕石",
      "ru": "Камни Разлома",
      "jp": "ブリーチストーン"
    },
    "name": {
      "en": "Uul-Netol's Pure Breachstone",
      "kr": "울네톨의 순수한 균열석",
      "tw": "烏爾尼多純淨裂痕石",
      "ru": "Очищенный камень Разлома Уул-Нетол",
      "jp": "ウール・ネトルの純化ブリーチストーン"
    },
    "dropLevel": 76,
    "spec": null,
    "currency": {
      "stackSize": 1,
      "description": {
        "en": "Rare Monsters drop an additional Reward Type\r\nArea has 2 additional random Modifiers\r\n150% increased Experience Gain\r\n60% increased Rarity of Items found in this Area\r\n60% increased Pack Size\r\nMonster Level: 82",
        "kr": "희귀 몬스터가 추가 보상 유형 1개 떨어뜨림\r\n지역에 무작위 속성 2개 추가\r\n경험치 획득량 150% 증가\r\n이 지역에서 발견하는 아이템의 희귀도 60% 증가\r\n무리 규모 60% 증가\r\n몬스터 레벨: 82",
        "tw": "稀有怪物掉落 1 個額外獎勵類型\r\n區域有 2 個額外隨機詞綴\r\n增加 150% 獲得經驗\r\n增加 60% 此區域的物品稀有度\r\n增加 60% 怪物群大小\r\n怪物等級：82",
        "ru": "Из редких монстров выпадает награда дополнительного типа\r\nНа область действуют 2 дополнительных случайных свойства\r\nУровень монстров: 82\r\n150% увеличение получаемого опыта\r\n60% повышение редкости найденных предметов в этой области\r\n60% увеличение размера групп монстров",
        "jp": "レアモンスターが追加の報酬タイプをドロップする\r\nエリアにランダムな2個のモッドが追加される\r\n得られる経験値が150%増加する\r\nエリア内で得られるアイテムのレアリティが60%増加する\r\nパックサイズが60%増加する\r\nモンスターレベル: 82"
      },
      "directions": {
        "en": "Travel to Uul-Netol's Domain by using this item in a personal Map Device. Can only be used once.",
        "kr": "전용 지도 장치에서 해당 아이템을 사용해 울네톨의 영토로 갈 수 있습니다. 한 번만 사용할 수 있습니다.",
        "tw": "透過個人的地圖裝置來使用此道具前往烏爾尼多領域。只能被使用一次。",
        "ru": "Используйте этот предмет в вашей Машине картоходца, чтобы отправиться во Владения Уул-Нетол. Можно использовать один раз.",
        "jp": "自身のマップデバイスでこのアイテムを使用してウール・ネトルの領域に移動する。一度のみ使用できる。"
      }
    },
    "flavour": null,
    "implicits": null,
    "image": null
  },
  {
    "id": "chayulas-pure-breachstone",
    "classId": "Breachstone",
    "className": {
      "en": "Breachstones",
      "kr": "균열석",
      "tw": "裂痕石",
      "ru": "Камни Разлома",
      "jp": "ブリーチストーン"
    },
    "name": {
      "en": "Chayula's Pure Breachstone",
      "kr": "차율라의 순수한 균열석",
      "tw": "夏烏拉純淨裂痕石",
      "ru": "Очищенный камень Разлома Чаюлы",
      "jp": "チャユラの純化ブリーチストーン"
    },
    "dropLevel": 80,
    "spec": null,
    "currency": {
      "stackSize": 1,
      "description": {
        "en": "Rare Monsters drop an additional Reward Type\r\nArea has 2 additional random Modifiers\r\n200% increased Experience Gain\r\n60% increased Rarity of Items found in this Area\r\n60% increased Pack Size\r\nMonster Level: 83",
        "kr": "희귀 몬스터가 추가 보상 유형 1개 떨어뜨림\r\n지역에 무작위 속성 2개 추가\r\n경험치 획득량 200% 증가\r\n이 지역에서 발견하는 아이템의 희귀도 60% 증가\r\n무리 규모 60% 증가\r\n몬스터 레벨: 83",
        "tw": "稀有怪物掉落 1 個額外獎勵類型\r\n區域有 2 個額外隨機詞綴\r\n增加 200% 獲得經驗\r\n增加 60% 此區域的物品稀有度\r\n增加 60% 怪物群大小\r\n怪物等級：83",
        "ru": "Из редких монстров выпадает награда дополнительного типа\r\nНа область действуют 2 дополнительных случайных свойства\r\nУровень монстров: 83\r\n200% увеличение получаемого опыта\r\n60% повышение редкости найденных предметов в этой области\r\n60% увеличение размера групп монстров",
        "jp": "レアモンスターが追加の報酬タイプをドロップする\r\nエリアにランダムな2個のモッドが追加される\r\n得られる経験値が200%増加する\r\nエリア内で得られるアイテムのレアリティが60%増加する\r\nパックサイズが60%増加する\r\nモンスターレベル: 83"
      },
      "directions": {
        "en": "Travel to Chayula's Domain by using this item in a personal Map Device. Can only be used once.",
        "kr": "전용 지도 장치에서 해당 아이템을 사용해 차율라의 영토로 갈 수 있습니다. 한 번만 사용할 수 있습니다.",
        "tw": "透過個人的地圖裝置來使用此道具前往夏烏拉領域。只能被使用一次。",
        "ru": "Используйте этот предмет в вашей Машине картоходца, чтобы отправиться во Владения Чаюлы. Можно использовать один раз.",
        "jp": "自身のマップデバイスでこのアイテムを使用してチャユラの領域に移動する。一度のみ使用できる。"
      }
    },
    "flavour": null,
    "implicits": null,
    "image": null
  },
  {
    "id": "xophs-flawless-breachstone",
    "classId": "Breachstone",
    "className": {
      "en": "Breachstones",
      "kr": "균열석",
      "tw": "裂痕石",
      "ru": "Камни Разлома",
      "jp": "ブリーチストーン"
    },
    "name": {
      "en": "Xoph's Flawless Breachstone",
      "kr": "조프의 결함 없는 균열석",
      "tw": "索伏無暇裂痕石",
      "ru": "Безупречный камень Разлома Ксофа",
      "jp": "ゾフの極限ブリーチストーン"
    },
    "dropLevel": 68,
    "spec": null,
    "currency": {
      "stackSize": 1,
      "description": {
        "en": "Rare Monsters drop 2 additional Reward Types\r\nArea has 4 additional random Modifiers\r\n200% increased Experience Gain\r\n250% more Monster Life\r\n60% increased Rarity of Items found in this Area\r\n60% increased Pack Size\r\nMonster Level: 84",
        "kr": "희귀 몬스터가 추가 보상 유형 2개 떨어뜨림\r\n지역에 무작위 속성 4개 추가\r\n경험치 획득량 200% 증가\r\n몬스터의 생명력 250% 증폭\r\n이 지역에서 발견하는 아이템의 희귀도 60% 증가\r\n무리 규모 60% 증가\r\n몬스터 레벨: 84",
        "tw": "稀有怪物掉落 2 個額外獎勵類型\r\n區域有 4 個額外隨機詞綴\r\n增加 200% 獲得經驗\r\n250% 更多怪物生命\r\n增加 60% 此區域的物品稀有度\r\n增加 60% 怪物群大小\r\n怪物等級：84",
        "ru": "Из редких монстров выпадает награда 2 дополнительных типов\r\nНа область действуют 4 дополнительных случайных свойства\r\n200% увеличение получаемого опыта\r\nНа 250% больше здоровья монстров\r\n60% повышение редкости найденных предметов в этой области\r\n60% увеличение размера групп монстров\r\nУровень монстров: 84",
        "jp": "レアモンスターが追加の報酬タイプを2個ドロップする\r\nエリアにランダムな4個のモッドが追加される\r\n得られる経験値が200%増加する\r\nモンスターのライフが250%上昇する\r\nエリア内で得られるアイテムのレアリティが60%増加する\r\nパックサイズが60%増加する\r\nモンスターレベル: 84"
      },
      "directions": {
        "en": "Travel to Xoph's Domain by using this item in a personal Map Device. Can only be used once.",
        "kr": "전용 지도 장치에서 해당 아이템을 사용해 조프의 영토로 갈 수 있습니다. 한 번만 사용할 수 있습니다.",
        "tw": "透過個人的地圖裝置來使用此道具前往索伏領域。只能被使用一次。",
        "ru": "Используйте этот предмет в вашей Машине картоходца, чтобы отправиться во Владения Ксофа. Можно использовать один раз.",
        "jp": "自身のマップデバイスでこのアイテムを使用してゾフの領域に移動する。一度のみ使用できる。"
      }
    },
    "flavour": null,
    "implicits": null,
    "image": null
  },
  {
    "id": "tuls-flawless-breachstone",
    "classId": "Breachstone",
    "className": {
      "en": "Breachstones",
      "kr": "균열석",
      "tw": "裂痕石",
      "ru": "Камни Разлома",
      "jp": "ブリーチストーン"
    },
    "name": {
      "en": "Tul's Flawless Breachstone",
      "kr": "툴의 결함 없는 균열석",
      "tw": "托沃無暇裂痕石",
      "ru": "Безупречный камень Разлома Тул",
      "jp": "トゥルの極限ブリーチストーン"
    },
    "dropLevel": 70,
    "spec": null,
    "currency": {
      "stackSize": 1,
      "description": {
        "en": "Rare Monsters drop 2 additional Reward Types\r\nArea has 4 additional random Modifiers\r\n200% increased Experience Gain\r\n250% more Monster Life\r\n60% increased Rarity of Items found in this Area\r\n60% increased Pack Size\r\nMonster Level: 84",
        "kr": "희귀 몬스터가 추가 보상 유형 2개 떨어뜨림\r\n지역에 무작위 속성 4개 추가\r\n경험치 획득량 200% 증가\r\n몬스터의 생명력 250% 증폭\r\n이 지역에서 발견하는 아이템의 희귀도 60% 증가\r\n무리 규모 60% 증가\r\n몬스터 레벨: 84",
        "tw": "稀有怪物掉落 2 個額外獎勵類型\r\n區域有 4 個額外隨機詞綴\r\n增加 200% 獲得經驗\r\n250% 更多怪物生命\r\n增加 60% 此區域的物品稀有度\r\n增加 60% 怪物群大小\r\n怪物等級：84",
        "ru": "Из редких монстров выпадает награда 2 дополнительных типов\r\nНа область действуют 4 дополнительных случайных свойства\r\n200% увеличение получаемого опыта\r\nНа 250% больше здоровья монстров\r\n60% повышение редкости найденных предметов в этой области\r\n60% увеличение размера групп монстров\r\nУровень монстров: 84",
        "jp": "レアモンスターが追加の報酬タイプを2個ドロップする\r\nエリアにランダムな4個のモッドが追加される\r\n得られる経験値が200%増加する\r\nモンスターのライフが250%上昇する\r\nエリア内で得られるアイテムのレアリティが60%増加する\r\nパックサイズが60%増加する\r\nモンスターレベル: 84"
      },
      "directions": {
        "en": "Travel to Tul's Domain by using this item in a personal Map Device. Can only be used once.",
        "kr": "전용 지도 장치에서 해당 아이템을 사용해 툴의 영토로 갈 수 있습니다. 한 번만 사용할 수 있습니다.",
        "tw": "透過個人的地圖裝置來使用此道具前往托沃領域。只能被使用一次。",
        "ru": "Используйте этот предмет в вашей Машине картоходца, чтобы отправиться во Владения Тул. Можно использовать один раз.",
        "jp": "自身のマップデバイスでこのアイテムを使用してトゥルの領域に移動する。一度のみ使用できる。"
      }
    },
    "flavour": null,
    "implicits": null,
    "image": null
  },
  {
    "id": "eshs-flawless-breachstone",
    "classId": "Breachstone",
    "className": {
      "en": "Breachstones",
      "kr": "균열석",
      "tw": "裂痕石",
      "ru": "Камни Разлома",
      "jp": "ブリーチストーン"
    },
    "name": {
      "en": "Esh's Flawless Breachstone",
      "kr": "에쉬의 결함 없는 균열석",
      "tw": "艾許無暇裂痕石",
      "ru": "Безупречный камень Разлома Иш",
      "jp": "エシュの極限ブリーチストーン"
    },
    "dropLevel": 72,
    "spec": null,
    "currency": {
      "stackSize": 1,
      "description": {
        "en": "Rare Monsters drop 2 additional Reward Types\r\nArea has 4 additional random Modifiers\r\n200% increased Experience Gain\r\n250% more Monster Life\r\n60% increased Rarity of Items found in this Area\r\n60% increased Pack Size\r\nMonster Level: 84",
        "kr": "희귀 몬스터가 추가 보상 유형 2개 떨어뜨림\r\n지역에 무작위 속성 4개 추가\r\n경험치 획득량 200% 증가\r\n몬스터의 생명력 250% 증폭\r\n이 지역에서 발견하는 아이템의 희귀도 60% 증가\r\n무리 규모 60% 증가\r\n몬스터 레벨: 84",
        "tw": "稀有怪物掉落 2 個額外獎勵類型\r\n區域有 4 個額外隨機詞綴\r\n增加 200% 獲得經驗\r\n250% 更多怪物生命\r\n增加 60% 此區域的物品稀有度\r\n增加 60% 怪物群大小\r\n怪物等級：84",
        "ru": "Из редких монстров выпадает награда 2 дополнительных типов\r\nНа область действуют 4 дополнительных случайных свойства\r\n200% увеличение получаемого опыта\r\nНа 250% больше здоровья монстров\r\n60% повышение редкости найденных предметов в этой области\r\n60% увеличение размера групп монстров\r\nУровень монстров: 84",
        "jp": "レアモンスターが追加の報酬タイプを2個ドロップする\r\nエリアにランダムな4個のモッドが追加される\r\n得られる経験値が200%増加する\r\nモンスターのライフが250%上昇する\r\nエリア内で得られるアイテムのレアリティが60%増加する\r\nパックサイズが60%増加する\r\nモンスターレベル: 84"
      },
      "directions": {
        "en": "Travel to Esh's Domain by using this item in a personal Map Device. Can only be used once.",
        "kr": "전용 지도 장치에서 해당 아이템을 사용해 에쉬의 영토로 갈 수 있습니다. 한 번만 사용할 수 있습니다.",
        "tw": "透過個人的地圖裝置來使用此道具前往艾許領域。只能被使用一次。",
        "ru": "Используйте этот предмет в вашей Машине картоходца, чтобы отправиться во Владения Иш. Можно использовать один раз.",
        "jp": "自身のマップデバイスでこのアイテムを使用してエシュの領域に移動する。一度のみ使用できる。"
      }
    },
    "flavour": null,
    "implicits": null,
    "image": null
  },
  {
    "id": "uul-netols-flawless-breachstone",
    "classId": "Breachstone",
    "className": {
      "en": "Breachstones",
      "kr": "균열석",
      "tw": "裂痕石",
      "ru": "Камни Разлома",
      "jp": "ブリーチストーン"
    },
    "name": {
      "en": "Uul-Netol's Flawless Breachstone",
      "kr": "울네톨의 결함 없는 균열석",
      "tw": "烏爾尼多無暇裂痕石",
      "ru": "Безупречный камень Разлома Уул-Нетол",
      "jp": "ウール・ネトルの極限ブリーチストーン"
    },
    "dropLevel": 76,
    "spec": null,
    "currency": {
      "stackSize": 1,
      "description": {
        "en": "Rare Monsters drop 2 additional Reward Types\r\nArea has 4 additional random Modifiers\r\n200% increased Experience Gain\r\n250% more Monster Life\r\n60% increased Rarity of Items found in this Area\r\n60% increased Pack Size\r\nMonster Level: 84",
        "kr": "희귀 몬스터가 추가 보상 유형 2개 떨어뜨림\r\n지역에 무작위 속성 4개 추가\r\n경험치 획득량 200% 증가\r\n몬스터의 생명력 250% 증폭\r\n이 지역에서 발견하는 아이템의 희귀도 60% 증가\r\n무리 규모 60% 증가\r\n몬스터 레벨: 84",
        "tw": "稀有怪物掉落 2 個額外獎勵類型\r\n區域有 4 個額外隨機詞綴\r\n增加 200% 獲得經驗\r\n250% 更多怪物生命\r\n增加 60% 此區域的物品稀有度\r\n增加 60% 怪物群大小\r\n怪物等級：84",
        "ru": "Из редких монстров выпадает награда 2 дополнительных типов\r\nНа область действуют 4 дополнительных случайных свойства\r\n200% увеличение получаемого опыта\r\nНа 250% больше здоровья монстров\r\n60% повышение редкости найденных предметов в этой области\r\n60% увеличение размера групп монстров\r\nУровень монстров: 84",
        "jp": "レアモンスターが追加の報酬タイプを2個ドロップする\r\nエリアにランダムな4個のモッドが追加される\r\n得られる経験値が200%増加する\r\nモンスターのライフが250%上昇する\r\nエリア内で得られるアイテムのレアリティが60%増加する\r\nパックサイズが60%増加する\r\nモンスターレベル: 84"
      },
      "directions": {
        "en": "Travel to Uul-Netol's Domain by using this item in a personal Map Device. Can only be used once.",
        "kr": "전용 지도 장치에서 해당 아이템을 사용해 울네톨의 영토로 갈 수 있습니다. 한 번만 사용할 수 있습니다.",
        "tw": "透過個人的地圖裝置來使用此道具前往烏爾尼多領域。只能被使用一次。",
        "ru": "Используйте этот предмет в вашей Машине картоходца, чтобы отправиться во Владения Уул-Нетол. Можно использовать один раз.",
        "jp": "自身のマップデバイスでこのアイテムを使用してウール・ネトルの領域に移動する。一度のみ使用できる。"
      }
    },
    "flavour": null,
    "implicits": null,
    "image": null
  },
  {
    "id": "chayulas-flawless-breachstone",
    "classId": "Breachstone",
    "className": {
      "en": "Breachstones",
      "kr": "균열석",
      "tw": "裂痕石",
      "ru": "Камни Разлома",
      "jp": "ブリーチストーン"
    },
    "name": {
      "en": "Chayula's Flawless Breachstone",
      "kr": "차율라의 결함 없는 균열석",
      "tw": "夏烏拉無暇裂痕石",
      "ru": "Безупречный камень Разлома Чаюлы",
      "jp": "チャユラの極限ブリーチストーン"
    },
    "dropLevel": 80,
    "spec": null,
    "currency": {
      "stackSize": 1,
      "description": {
        "en": "Rare Monsters drop 2 additional Reward Types\r\nArea has 4 additional random Modifiers\r\n200% increased Experience Gain\r\n250% more Monster Life\r\n60% increased Rarity of Items found in this Area\r\n60% increased Pack Size\r\nMonster Level: 84",
        "kr": "희귀 몬스터가 추가 보상 유형 2개 떨어뜨림\r\n지역에 무작위 속성 4개 추가\r\n경험치 획득량 200% 증가\r\n몬스터의 생명력 250% 증폭\r\n이 지역에서 발견하는 아이템의 희귀도 60% 증가\r\n무리 규모 60% 증가\r\n몬스터 레벨: 84",
        "tw": "稀有怪物掉落 2 個額外獎勵類型\r\n區域有 4 個額外隨機詞綴\r\n增加 200% 獲得經驗\r\n250% 更多怪物生命\r\n增加 60% 此區域的物品稀有度\r\n增加 60% 怪物群大小\r\n怪物等級：84",
        "ru": "Из редких монстров выпадает награда 2 дополнительных типов\r\nНа область действуют 4 дополнительных случайных свойства\r\n200% увеличение получаемого опыта\r\nНа 250% больше здоровья монстров\r\n60% повышение редкости найденных предметов в этой области\r\n60% увеличение размера групп монстров\r\nУровень монстров: 84",
        "jp": "レアモンスターが追加の報酬タイプを2個ドロップする\r\nエリアにランダムな4個のモッドが追加される\r\n得られる経験値が200%増加する\r\nモンスターのライフが250%上昇する\r\nエリア内で得られるアイテムのレアリティが60%増加する\r\nパックサイズが60%増加する\r\nモンスターレベル: 84"
      },
      "directions": {
        "en": "Travel to Chayula's Domain by using this item in a personal Map Device. Can only be used once.",
        "kr": "전용 지도 장치에서 해당 아이템을 사용해 차율라의 영토로 갈 수 있습니다. 한 번만 사용할 수 있습니다.",
        "tw": "透過個人的地圖裝置來使用此道具前往夏烏拉領域。只能被使用一次。",
        "ru": "Используйте этот предмет в вашей Машине картоходца, чтобы отправиться во Владения Чаюлы. Можно использовать один раз.",
        "jp": "自身のマップデバイスでこのアイテムを使用してチャユラの領域に移動する。一度のみ使用できる。"
      }
    },
    "flavour": null,
    "implicits": null,
    "image": null
  }
]