[
  {
    "id": "archon-kite-shield-piece",
    "classId": "UniqueFragment",
    "className": {
      "en": "Pieces",
      "kr": "조각",
      "tw": "碎片",
      "ru": "Фрагменты",
      "jp": "ユニークのピース"
    },
    "name": {
      "en": "Archon Kite Shield Piece",
      "kr": "집정관의 연모양 방패 조각",
      "tw": "威能鳶盾碎片",
      "ru": "Часть каплевидного щита архонта",
      "jp": "アルコンカイトシールドの欠片"
    },
    "dropLevel": 1,
    "spec": null,
    "currency": null,
    "flavour": null,
    "implicits": null,
    "image": null
  },
  {
    "id": "archon-kite-shield-piece",
    "classId": "UniqueFragment",
    "className": {
      "en": "Pieces",
      "kr": "조각",
      "tw": "碎片",
      "ru": "Фрагменты",
      "jp": "ユニークのピース"
    },
    "name": {
      "en": "Archon Kite Shield Piece",
      "kr": "집정관의 연모양 방패 조각",
      "tw": "威能鳶盾碎片",
      "ru": "Часть каплевидного щита архонта",
      "jp": "アルコンカイトシールドの欠片"
    },
    "dropLevel": 1,
    "spec": null,
    "currency": null,
    "flavour": null,
    "implicits": null,
    "image": null
  },
  {
    "id": "archon-kite-shield-piece",
    "classId": "UniqueFragment",
    "className": {
      "en": "Pieces",
      "kr": "조각",
      "tw": "碎片",
      "ru": "Фрагменты",
      "jp": "ユニークのピース"
    },
    "name": {
      "en": "Archon Kite Shield Piece",
      "kr": "집정관의 연모양 방패 조각",
      "tw": "威能鳶盾碎片",
      "ru": "Часть каплевидного щита архонта",
      "jp": "アルコンカイトシールドの欠片"
    },
    "dropLevel": 1,
    "spec": null,
    "currency": null,
    "flavour": null,
    "implicits": null,
    "image": null
  },
  {
    "id": "archon-kite-shield-piece",
    "classId": "UniqueFragment",
    "className": {
      "en": "Pieces",
      "kr": "조각",
      "tw": "碎片",
      "ru": "Фрагменты",
      "jp": "ユニークのピース"
    },
    "name": {
      "en": "Archon Kite Shield Piece",
      "kr": "집정관의 연모양 방패 조각",
      "tw": "威能鳶盾碎片",
      "ru": "Часть каплевидного щита архонта",
      "jp": "アルコンカイトシールドの欠片"
    },
    "dropLevel": 1,
    "spec": null,
    "currency": null,
    "flavour": null,
    "implicits": null,
    "image": null
  },
  {
    "id": "legion-sword-piece",
    "classId": "UniqueFragment",
    "className": {
      "en": "Pieces",
      "kr": "조각",
      "tw": "碎片",
      "ru": "Фрагменты",
      "jp": "ユニークのピース"
    },
    "name": {
      "en": "Legion Sword Piece",
      "kr": "군단 검 조각",
      "tw": "軍團長劍碎片",
      "ru": "Часть меча всадника",
      "jp": "リージョンソードの欠片"
    },
    "dropLevel": 1,
    "spec": null,
    "currency": null,
    "flavour": null,
    "implicits": null,
    "image": null
  },
  {
    "id": "legion-sword-piece",
    "classId": "UniqueFragment",
    "className": {
      "en": "Pieces",
      "kr": "조각",
      "tw": "碎片",
      "ru": "Фрагменты",
      "jp": "ユニークのピース"
    },
    "name": {
      "en": "Legion Sword Piece",
      "kr": "군단 검 조각",
      "tw": "軍團長劍碎片",
      "ru": "Часть меча всадника",
      "jp": "リージョンソードの欠片"
    },
    "dropLevel": 1,
    "spec": null,
    "currency": null,
    "flavour": null,
    "implicits": null,
    "image": null
  },
  {
    "id": "legion-sword-piece",
    "classId": "UniqueFragment",
    "className": {
      "en": "Pieces",
      "kr": "조각",
      "tw": "碎片",
      "ru": "Фрагменты",
      "jp": "ユニークのピース"
    },
    "name": {
      "en": "Legion Sword Piece",
      "kr": "군단 검 조각",
      "tw": "軍團長劍碎片",
      "ru": "Часть меча всадника",
      "jp": "リージョンソードの欠片"
    },
    "dropLevel": 1,
    "spec": null,
    "currency": null,
    "flavour": null,
    "implicits": null,
    "image": null
  },
  {
    "id": "imperial-staff-piece",
    "classId": "UniqueFragment",
    "className": {
      "en": "Pieces",
      "kr": "조각",
      "tw": "碎片",
      "ru": "Фрагменты",
      "jp": "ユニークのピース"
    },
    "name": {
      "en": "Imperial Staff Piece",
      "kr": "제국 지팡이 조각",
      "tw": "帝國長杖碎片",
      "ru": "Часть императорского посоха",
      "jp": "インペリアルスタッフの欠片"
    },
    "dropLevel": 1,
    "spec": null,
    "currency": null,
    "flavour": null,
    "implicits": null,
    "image": null
  },
  {
    "id": "imperial-staff-piece",
    "classId": "UniqueFragment",
    "className": {
      "en": "Pieces",
      "kr": "조각",
      "tw": "碎片",
      "ru": "Фрагменты",
      "jp": "ユニークのピース"
    },
    "name": {
      "en": "Imperial Staff Piece",
      "kr": "제국 지팡이 조각",
      "tw": "帝國長杖碎片",
      "ru": "Часть императорского посоха",
      "jp": "インペリアルスタッフの欠片"
    },
    "dropLevel": 1,
    "spec": null,
    "currency": null,
    "flavour": null,
    "implicits": null,
    "image": null
  },
  {
    "id": "imperial-staff-piece",
    "classId": "UniqueFragment",
    "className": {
      "en": "Pieces",
      "kr": "조각",
      "tw": "碎片",
      "ru": "Фрагменты",
      "jp": "ユニークのピース"
    },
    "name": {
      "en": "Imperial Staff Piece",
      "kr": "제국 지팡이 조각",
      "tw": "帝國長杖碎片",
      "ru": "Часть императорского посоха",
      "jp": "インペリアルスタッフの欠片"
    },
    "dropLevel": 1,
    "spec": null,
    "currency": null,
    "flavour": null,
    "implicits": null,
    "image": null
  },
  {
    "id": "cloth-belt-piece",
    "classId": "UniqueFragment",
    "className": {
      "en": "Pieces",
      "kr": "조각",
      "tw": "碎片",
      "ru": "Фрагменты",
      "jp": "ユニークのピース"
    },
    "name": {
      "en": "Cloth Belt Piece",
      "kr": "헝겊 허리띠 조각",
      "tw": "飾布腰帶碎片",
      "ru": "Часть матерчатого пояса",
      "jp": "布のベルトの欠片"
    },
    "dropLevel": 1,
    "spec": null,
    "currency": null,
    "flavour": null,
    "implicits": null,
    "image": null
  },
  {
    "id": "cloth-belt-piece",
    "classId": "UniqueFragment",
    "className": {
      "en": "Pieces",
      "kr": "조각",
      "tw": "碎片",
      "ru": "Фрагменты",
      "jp": "ユニークのピース"
    },
    "name": {
      "en": "Cloth Belt Piece",
      "kr": "헝겊 허리띠 조각",
      "tw": "飾布腰帶碎片",
      "ru": "Часть матерчатого пояса",
      "jp": "布のベルトの欠片"
    },
    "dropLevel": 1,
    "spec": null,
    "currency": null,
    "flavour": null,
    "implicits": null,
    "image": null
  },
  {
    "id": "blunt-arrow-quiver-piece",
    "classId": "UniqueFragment",
    "className": {
      "en": "Pieces",
      "kr": "조각",
      "tw": "碎片",
      "ru": "Фрагменты",
      "jp": "ユニークのピース"
    },
    "name": {
      "en": "Blunt Arrow Quiver Piece",
      "kr": "뭉툭한 화살통 조각",
      "tw": "鈍矢箭袋碎片",
      "ru": "Часть колчана промысловых стрел",
      "jp": "鈍頭の矢筒の欠片"
    },
    "dropLevel": 1,
    "spec": null,
    "currency": null,
    "flavour": null,
    "implicits": null,
    "image": null
  },
  {
    "id": "blunt-arrow-quiver-piece",
    "classId": "UniqueFragment",
    "className": {
      "en": "Pieces",
      "kr": "조각",
      "tw": "碎片",
      "ru": "Фрагменты",
      "jp": "ユニークのピース"
    },
    "name": {
      "en": "Blunt Arrow Quiver Piece",
      "kr": "뭉툭한 화살통 조각",
      "tw": "鈍矢箭袋碎片",
      "ru": "Часть колчана промысловых стрел",
      "jp": "鈍頭の矢筒の欠片"
    },
    "dropLevel": 1,
    "spec": null,
    "currency": null,
    "flavour": null,
    "implicits": null,
    "image": null
  },
  {
    "id": "blunt-arrow-quiver-piece",
    "classId": "UniqueFragment",
    "className": {
      "en": "Pieces",
      "kr": "조각",
      "tw": "碎片",
      "ru": "Фрагменты",
      "jp": "ユニークのピース"
    },
    "name": {
      "en": "Blunt Arrow Quiver Piece",
      "kr": "뭉툭한 화살통 조각",
      "tw": "鈍矢箭袋碎片",
      "ru": "Часть колчана промысловых стрел",
      "jp": "鈍頭の矢筒の欠片"
    },
    "dropLevel": 1,
    "spec": null,
    "currency": null,
    "flavour": null,
    "implicits": null,
    "image": null
  },
  {
    "id": "callous-mask-piece",
    "classId": "UniqueFragment",
    "className": {
      "en": "Pieces",
      "kr": "조각",
      "tw": "碎片",
      "ru": "Фрагменты",
      "jp": "ユニークのピース"
    },
    "name": {
      "en": "Callous Mask Piece",
      "kr": "냉담한 가면 조각",
      "tw": "無情之面碎片",
      "ru": "Часть маски равнодушия",
      "jp": "無情のマスクの欠片"
    },
    "dropLevel": 1,
    "spec": null,
    "currency": null,
    "flavour": null,
    "implicits": null,
    "image": null
  },
  {
    "id": "callous-mask-piece",
    "classId": "UniqueFragment",
    "className": {
      "en": "Pieces",
      "kr": "조각",
      "tw": "碎片",
      "ru": "Фрагменты",
      "jp": "ユニークのピース"
    },
    "name": {
      "en": "Callous Mask Piece",
      "kr": "냉담한 가면 조각",
      "tw": "無情之面碎片",
      "ru": "Часть маски равнодушия",
      "jp": "無情のマスクの欠片"
    },
    "dropLevel": 1,
    "spec": null,
    "currency": null,
    "flavour": null,
    "implicits": null,
    "image": null
  },
  {
    "id": "callous-mask-piece",
    "classId": "UniqueFragment",
    "className": {
      "en": "Pieces",
      "kr": "조각",
      "tw": "碎片",
      "ru": "Фрагменты",
      "jp": "ユニークのピース"
    },
    "name": {
      "en": "Callous Mask Piece",
      "kr": "냉담한 가면 조각",
      "tw": "無情之面碎片",
      "ru": "Часть маски равнодушия",
      "jp": "無情のマスクの欠片"
    },
    "dropLevel": 1,
    "spec": null,
    "currency": null,
    "flavour": null,
    "implicits": null,
    "image": null
  },
  {
    "id": "vaal-aspect",
    "classId": "UniqueFragment",
    "className": {
      "en": "Pieces",
      "kr": "조각",
      "tw": "碎片",
      "ru": "Фрагменты",
      "jp": "ユニークのピース"
    },
    "name": {
      "en": "Vaal Aspect",
      "kr": "바알 위상",
      "tw": "瓦爾祝福",
      "ru": "Аспект ваал",
      "jp": "ヴァールアスペクト"
    },
    "dropLevel": 1,
    "spec": null,
    "currency": null,
    "flavour": {
      "en": "They took pride in all that they built, considering each new\r\ntemple a testament to the gods... and then, to themselves.",
      "kr": "그들은 자신들이 세운 모든 것을 자랑스럽게 여기며, 새로운 신전 하나하나를\r\n신들의... 그리고 자신들의 힘에 대한 증거로 여겼다.",
      "tw": "你離開時流血而精疲力竭，但勝利了。\r\n你已經戰勝了。",
      "ru": "Они гордились всем, что построили, считая каждый новый храм\r\nзавещанием богам... а затем – самим себе.",
      "jp": "彼らは築き上げたもの全てを誇りに思い、新たな寺院を\r\n建てる度にそれを神々に……そして自らに捧げた。"
    },
    "implicits": null,
    "image": null
  },
  {
    "id": "vaal-aspect",
    "classId": "UniqueFragment",
    "className": {
      "en": "Pieces",
      "kr": "조각",
      "tw": "碎片",
      "ru": "Фрагменты",
      "jp": "ユニークのピース"
    },
    "name": {
      "en": "Vaal Aspect",
      "kr": "바알 위상",
      "tw": "瓦爾祝福",
      "ru": "Аспект ваал",
      "jp": "ヴァールアスペクト"
    },
    "dropLevel": 1,
    "spec": null,
    "currency": null,
    "flavour": {
      "en": "Delving into the mysteries of existence, they deciphered\r\nthe secret laws of nature... and then, harnessed them.",
      "kr": "존재의 수수께끼를 탐구하던 그들은 자연의 비밀스러운\r\n규칙을 해독하고... 이를 자신들의 힘으로 삼았다.",
      "tw": "你破碎的身體被遺忘了，\r\n只滋養著蟲群。",
      "ru": "Погружаясь в загадки мироздания, они расшифровали\r\nтайные законы природы... а затем обуздали их.",
      "jp": "現実の謎を追求し、彼らは自然の\r\n秘密の法則を読み解き……そして利用した。"
    },
    "implicits": null,
    "image": null
  },
  {
    "id": "vaal-aspect",
    "classId": "UniqueFragment",
    "className": {
      "en": "Pieces",
      "kr": "조각",
      "tw": "碎片",
      "ru": "Фрагменты",
      "jp": "ユニークのピース"
    },
    "name": {
      "en": "Vaal Aspect",
      "kr": "바알 위상",
      "tw": "瓦爾祝福",
      "ru": "Аспект ваал",
      "jp": "ヴァールアスペクト"
    },
    "dropLevel": 1,
    "spec": null,
    "currency": null,
    "flavour": {
      "en": "Not content to live in harmony with the world, they strove\r\nto understand it, to improve it... and then, to master it.",
      "kr": "이 세상과 조화를 이루는 삶에 만족하지 못한 그들은\r\n자연을 이해하고, 개선하고... 종국엔 그 주인이 되고자 했다.",
      "tw": "凡人終其一生都在想，哪一種命運\r\n將屬於他們。混沌樂於\r\n知道答案：所有人。",
      "ru": "Не удовлетворившись жизнью в гармонии с миром, они стремились\r\nпонять его, улучшить его... а затем подчинить его.",
      "jp": "世界と調和した生き方に満足せず、彼らは世界を\r\n理解し、改善し……そして掌握しようとした。"
    },
    "implicits": null,
    "image": null
  },
  {
    "id": "vaal-aspect",
    "classId": "UniqueFragment",
    "className": {
      "en": "Pieces",
      "kr": "조각",
      "tw": "碎片",
      "ru": "Фрагменты",
      "jp": "ユニークのピース"
    },
    "name": {
      "en": "Vaal Aspect",
      "kr": "바알 위상",
      "tw": "瓦爾祝福",
      "ru": "Аспект ваал",
      "jp": "ヴァールアスペクト"
    },
    "dropLevel": 1,
    "spec": null,
    "currency": null,
    "flavour": {
      "en": "They collaborated with each other and with nearby peoples,\r\nat first sharing, teaching... and then, dominating.",
      "kr": "그들은 서로 그리고 주변의 민족들과 협력했다.\r\n처음에는 나누고 가르쳤으나... 이내 그들 위에 군림하게 되었다.",
      "tw": "你踉踉蹌蹌地走開，為你的失敗感到尷尬。\r\n你唯一的安慰獎就是你的生命。",
      "ru": "Они сотрудничали друг с другом и с ближайшими народами,\r\nсначала делясь, обучая... а затем порабощая.",
      "jp": "彼らはお互いや隣人と協力し、初めは分け与え、\r\n教え導き……そして支配した。"
    },
    "implicits": null,
    "image": null
  },
  {
    "id": "primordial-fragment",
    "classId": "UniqueFragment",
    "className": {
      "en": "Pieces",
      "kr": "조각",
      "tw": "碎片",
      "ru": "Фрагменты",
      "jp": "ユニークのピース"
    },
    "name": {
      "en": "Primordial Fragment",
      "kr": "태고의 조각",
      "tw": "先祖碎片",
      "ru": "Первобытный фрагмент",
      "jp": "創世の欠片"
    },
    "dropLevel": 1,
    "spec": null,
    "currency": null,
    "flavour": null,
    "implicits": null,
    "image": null
  },
  {
    "id": "primordial-fragment",
    "classId": "UniqueFragment",
    "className": {
      "en": "Pieces",
      "kr": "조각",
      "tw": "碎片",
      "ru": "Фрагменты",
      "jp": "ユニークのピース"
    },
    "name": {
      "en": "Primordial Fragment",
      "kr": "태고의 조각",
      "tw": "先祖碎片",
      "ru": "Первобытный фрагмент",
      "jp": "創世の欠片"
    },
    "dropLevel": 1,
    "spec": null,
    "currency": null,
    "flavour": null,
    "implicits": null,
    "image": null
  },
  {
    "id": "primordial-fragment",
    "classId": "UniqueFragment",
    "className": {
      "en": "Pieces",
      "kr": "조각",
      "tw": "碎片",
      "ru": "Фрагменты",
      "jp": "ユニークのピース"
    },
    "name": {
      "en": "Primordial Fragment",
      "kr": "태고의 조각",
      "tw": "先祖碎片",
      "ru": "Первобытный фрагмент",
      "jp": "創世の欠片"
    },
    "dropLevel": 1,
    "spec": null,
    "currency": null,
    "flavour": null,
    "implicits": null,
    "image": null
  },
  {
    "id": "primordial-fragment",
    "classId": "UniqueFragment",
    "className": {
      "en": "Pieces",
      "kr": "조각",
      "tw": "碎片",
      "ru": "Фрагменты",
      "jp": "ユニークのピース"
    },
    "name": {
      "en": "Primordial Fragment",
      "kr": "태고의 조각",
      "tw": "先祖碎片",
      "ru": "Первобытный фрагмент",
      "jp": "創世の欠片"
    },
    "dropLevel": 1,
    "spec": null,
    "currency": null,
    "flavour": null,
    "implicits": null,
    "image": null
  }
]